[{"experienceLevel":"Expérience requise : 1 à 3 ans","niveauEtude":"Niveau d’étude demandé : Bac+3","jobTitle":"Fonction : Juriste droit des affaires","skills":["Secteur","d\u0027activité",":","Banque","assurance"]},{"experienceLevel":"Expérience requise : 10 à 20 ans","niveauEtude":"Niveau d’étude demandé : Bac+5 et plus","jobTitle":"Fonction : RAF","skills":["Secteur","d\u0027activité",":","BTP","construction"]},{"experienceLevel":"Expérience requise : 3 à 5 ans","niveauEtude":"Niveau d’étude demandé : Bac+3","jobTitle":"Fonction : Hospitality Officer","skills":["Secteur","d\u0027activité",":","Évènementiel","hôte(sse)","accueil"]},{"experienceLevel":"Expérience requise : 5 à 10 ans","niveauEtude":"Niveau d’étude demandé : Bac+5 et plus","jobTitle":"Fonction : Ingénieur génie civil senior sidi rahal","skills":["Secteur","d\u0027activité",":","BTP","construction"]},{"experienceLevel":"Expérience requise : 1 à 3 ans","niveauEtude":"Niveau d’étude demandé : Bac+2","jobTitle":"Fonction : controle qualite","skills":["Secteur","d\u0027activité",":","Industrie","production","fabrication","autres"]},{"experienceLevel":"Expérience requise : 3 à 5 ans","niveauEtude":"Niveau d’étude demandé : Bac+2","jobTitle":"Fonction : Technicien IT","skills":["Secteur","d\u0027activité",":","BTP","construction"]},{"experienceLevel":"Expérience requise : 5 à 10 ans","niveauEtude":"Niveau d’étude demandé : Bac+5 et plus","jobTitle":"Fonction : Responsable de la Technologie et de l’infrastructure IT des Sites","skills":["Secteur","d\u0027activité",":","Equip.","électriques","électroniques","optiques","précision"]},{"experienceLevel":"Expérience requise : 1 à 3 ans","niveauEtude":"Niveau d’étude demandé : Bac+5 et plus","jobTitle":"Fonction : Chargé(e) de Marketing Digital - CDI","skills":["Secteur","d\u0027activité",":","Import","export"]},{"experienceLevel":"Expérience requise : 5 à 10 ans","niveauEtude":"Niveau d’étude demandé : Bac+5 et plus","jobTitle":"Fonction : Un(e) Commercial(e) Prescripteur Senior - CDI","skills":["Secteur","d\u0027activité",":","Import","export"]},{"experienceLevel":"Expérience requise : 1 à 3 ans","niveauEtude":"Niveau d’étude demandé : Bac+2","jobTitle":"Fonction : CAVISTE","skills":["Secteur","d\u0027activité",":","Hôtellerie","restauration"]}]